wandb_osh/__init__.py
wandb_osh/cli.py
wandb_osh/config.py
wandb_osh/hooks.py
wandb_osh/lightning_hooks.py
wandb_osh/ray_hooks.py
wandb_osh/syncer.py
wandb_osh/util/__init__.py
wandb_osh/util/hash_id.py
wandb_osh/util/log.py
wandb_osh-1.2.2.dist-info/LICENSE.txt
wandb_osh-1.2.2.dist-info/METADATA
wandb_osh-1.2.2.dist-info/WHEEL
wandb_osh-1.2.2.dist-info/entry_points.txt
wandb_osh-1.2.2.dist-info/top_level.txt
wandb_osh-1.2.2.dist-info/RECORD
