Metadata-Version: 2.1
Name: wandb_osh
Version: 1.2.2
Summary: Trigger wandb offline syncs from a compute node without internet
Home-page: https://github.com/klieret/wandb-offline-sync-hook
Author: Kilian Lieret
Author-email: kilian.lieret@posteo.de
Maintainer: Kilian Lieret
Maintainer-email: kilian.lieret@posteo.de
License: MIT
Project-URL: Bug Tracker, https://github.com/klieret/wandb-offline-sync-hook/issues
Project-URL: Documentation, https://wandb_osh.readthedocs.io/
Project-URL: Source Code, https://github.com/klieret/wandb-offline-sync-hook
Classifier: License :: OSI Approved :: MIT License
Classifier: Operating System :: OS Independent
Classifier: Programming Language :: Python :: 3
Classifier: Programming Language :: Python :: 3 :: Only
Classifier: Programming Language :: Python :: 3.8
Classifier: Programming Language :: Python :: 3.9
Classifier: Programming Language :: Python :: 3.10
Requires-Python: >=3.8
License-File: LICENSE.txt
Requires-Dist: colorlog
Requires-Dist: wandb
Requires-Dist: importlib-metadata >=0.12 ; python_version < "3.8"
Provides-Extra: lightning
Requires-Dist: lightning ; extra == 'lightning'
Provides-Extra: ray
Requires-Dist: ray[tune] ; extra == 'ray'
Provides-Extra: testing
Requires-Dist: pytest ; extra == 'testing'
Requires-Dist: pytest-coverage ; extra == 'testing'
